{"num_predictions": [{"arco-herradura": 0}, {"dintel-adovelado": 0}, {"arco-lobulado": 0}, {"arco-medio-punto": 1}, {"arco-apuntado": 0}, {"vano-adintelado": 1}, {"fronton": 1}, {"arco-conopial": 0}, {"arco-trilobulado": 0}, {"serliana": 0}, {"ojo-de-buey": 0}, {"fronton-curvo": 1}, {"fronton-partido": 3}, {"columna-salomonica": 0}], "image": "../Data/Dataset-IGRB1092_14cls/04.barroco/5bd33eb67044c.jpg", "object": [{"bndbox": {"xmin": "0.26354557", "ymin": "0.14372556", "ymax": "0.35632238", "xmax": "0.7625404"}, "score": "0.9941273", "class": "fronton-partido"}, {"bndbox": {"xmin": "0.37196383", "ymin": "0.391436", "ymax": "0.6039025", "xmax": "0.68016034"}, "score": "0.9927256", "class": "arco-medio-punto"}, {"bndbox": {"xmin": "0.42566055", "ymin": "0.0", "ymax": "0.06777142", "xmax": "0.6200039"}, "score": "0.8540953", "class": "fronton-curvo"}, {"bndbox": {"xmin": "0.4550263", "ymin": "0.055948135", "ymax": "0.2730507", "xmax": "0.5824055"}, "score": "0.62017614", "class": "vano-adintelado"}, {"bndbox": {"xmin": "0.4015387", "ymin": "0.0", "ymax": "0.07409512", "xmax": "0.624123"}, "score": "0.45089924", "class": "fronton-partido"}, {"bndbox": {"xmin": "0.4027819", "ymin": "0.0", "ymax": "0.066730574", "xmax": "0.62939566"}, "score": "0.3226155", "class": "fronton"}, {"bndbox": {"xmin": "0.28431", "ymin": "0.10001594", "ymax": "0.27151287", "xmax": "0.72311133"}, "score": "0.08672591", "class": "fronton-partido"}], "true_label": 3}