{"num_predictions": [{"arco-herradura": 0}, {"dintel-adovelado": 0}, {"arco-lobulado": 0}, {"arco-medio-punto": 8}, {"arco-apuntado": 0}, {"vano-adintelado": 0}, {"fronton": 0}, {"arco-conopial": 0}, {"arco-trilobulado": 0}, {"serliana": 4}, {"ojo-de-buey": 0}, {"fronton-curvo": 0}, {"fronton-partido": 2}, {"columna-salomonica": 0}], "image": "../Data/Dataset-IGRB1092_14cls/04.barroco/catedral_granada4.jpg", "object": [{"bndbox": {"xmin": "0.38098115", "ymin": "0.091304444", "ymax": "0.3386577", "xmax": "0.6956195"}, "score": "0.9629108", "class": "arco-medio-punto"}, {"bndbox": {"xmin": "0.47054818", "ymin": "0.8266861", "ymax": "1.0", "xmax": "0.7534579"}, "score": "0.6678732", "class": "arco-medio-punto"}, {"bndbox": {"xmin": "0.73867756", "ymin": "0.25487477", "ymax": "0.44617504", "xmax": "0.9748794"}, "score": "0.6321242", "class": "arco-medio-punto"}, {"bndbox": {"xmin": "0.122232616", "ymin": "0.2329788", "ymax": "0.42234161", "xmax": "0.34507203"}, "score": "0.3863234", "class": "arco-medio-punto"}, {"bndbox": {"xmin": "0.4629021", "ymin": "0.8423375", "ymax": "0.97734785", "xmax": "0.60305256"}, "score": "0.15108384", "class": "arco-medio-punto"}, {"bndbox": {"xmin": "0.5400545", "ymin": "0.83858764", "ymax": "0.9904474", "xmax": "0.69491816"}, "score": "0.12424552", "class": "serliana"}, {"bndbox": {"xmin": "0.4747627", "ymin": "0.82647425", "ymax": "0.99854344", "xmax": "0.7537492"}, "score": "0.0879894", "class": "serliana"}, {"bndbox": {"xmin": "0.38088563", "ymin": "0.34241334", "ymax": "0.68613625", "xmax": "0.68569577"}, "score": "0.07650146", "class": "arco-medio-punto"}, {"bndbox": {"xmin": "0.2629381", "ymin": "0.0034877039", "ymax": "0.0782116", "xmax": "0.9926552"}, "score": "0.06728764", "class": "fronton-partido"}, {"bndbox": {"xmin": "0.0824161", "ymin": "0.20478027", "ymax": "0.9805478", "xmax": "0.6903942"}, "score": "0.06236605", "class": "serliana"}, {"bndbox": {"xmin": "0.20251927", "ymin": "0.81883657", "ymax": "1.0", "xmax": "0.40700278"}, "score": "0.056445986", "class": "arco-medio-punto"}, {"bndbox": {"xmin": "0.46669707", "ymin": "0.8616644", "ymax": "1.0", "xmax": "0.837351"}, "score": "0.05638096", "class": "fronton-partido"}, {"bndbox": {"xmin": "0.1793599", "ymin": "0.8368338", "ymax": "0.99373484", "xmax": "0.6891875"}, "score": "0.055578556", "class": "serliana"}, {"bndbox": {"xmin": "0.53692055", "ymin": "0.847216", "ymax": "1.0", "xmax": "0.6699837"}, "score": "0.052415248", "class": "arco-medio-punto"}], "true_label": 3}