{"num_predictions": [{"arco-herradura": 3}, {"dintel-adovelado": 2}, {"arco-lobulado": 0}, {"arco-medio-punto": 3}, {"arco-apuntado": 0}, {"vano-adintelado": 0}, {"fronton": 0}, {"arco-conopial": 0}, {"arco-trilobulado": 0}, {"serliana": 0}, {"ojo-de-buey": 2}, {"fronton-curvo": 0}, {"fronton-partido": 0}, {"columna-salomonica": 0}], "image": "../Data/Dataset-IGRB1092_14cls/01.musulman/puerta_del_vino_granada8.jpg", "object": [{"bndbox": {"xmin": "0.28261152", "ymin": "0.5086161", "ymax": "0.7891688", "xmax": "0.6556783"}, "score": "0.99769324", "class": "arco-herradura"}, {"bndbox": {"xmin": "0.2604104", "ymin": "0.371303", "ymax": "0.4581039", "xmax": "0.6638517"}, "score": "0.9954384", "class": "dintel-adovelado"}, {"bndbox": {"xmin": "0.45195985", "ymin": "0.15230611", "ymax": "0.21936485", "xmax": "0.5334093"}, "score": "0.63905406", "class": "ojo-de-buey"}, {"bndbox": {"xmin": "0.3680368", "ymin": "0.15651093", "ymax": "0.23080964", "xmax": "0.44491896"}, "score": "0.5210146", "class": "arco-herradura"}, {"bndbox": {"xmin": "0.28528515", "ymin": "0.5060804", "ymax": "0.763214", "xmax": "0.6673354"}, "score": "0.4180625", "class": "arco-medio-punto"}, {"bndbox": {"xmin": "0.45336446", "ymin": "0.15241294", "ymax": "0.23132469", "xmax": "0.5352595"}, "score": "0.30044246", "class": "arco-herradura"}, {"bndbox": {"xmin": "0.36564234", "ymin": "0.15515926", "ymax": "0.22159722", "xmax": "0.44526213"}, "score": "0.28590167", "class": "arco-medio-punto"}, {"bndbox": {"xmin": "0.36626348", "ymin": "0.15692742", "ymax": "0.21903463", "xmax": "0.4434555"}, "score": "0.24336208", "class": "ojo-de-buey"}, {"bndbox": {"xmin": "0.44780877", "ymin": "0.14928876", "ymax": "0.22467121", "xmax": "0.5324816"}, "score": "0.15240376", "class": "arco-medio-punto"}, {"bndbox": {"xmin": "0.19635013", "ymin": "0.31408498", "ymax": "0.46122473", "xmax": "0.7270247"}, "score": "0.09721281", "class": "dintel-adovelado"}], "true_label": 0}