{"num_predictions": [{"arco-herradura": 0}, {"dintel-adovelado": 0}, {"arco-lobulado": 0}, {"arco-medio-punto": 0}, {"arco-apuntado": 0}, {"vano-adintelado": 1}, {"fronton": 1}, {"arco-conopial": 0}, {"arco-trilobulado": 0}, {"serliana": 0}, {"ojo-de-buey": 0}, {"fronton-curvo": 0}, {"fronton-partido": 2}, {"columna-salomonica": 0}], "image": "../Data/Dataset-IGRB1092_14cls/04.barroco/5bd5754e6f78b.jpg", "object": [{"bndbox": {"xmin": "0.24448214", "ymin": "0.31626305", "ymax": "1.0", "xmax": "0.75904703"}, "score": "0.9993229", "class": "vano-adintelado"}, {"bndbox": {"xmin": "0.16908261", "ymin": "0.13146174", "ymax": "0.24563341", "xmax": "0.86406374"}, "score": "0.98288107", "class": "fronton-partido"}, {"bndbox": {"xmin": "0.16702126", "ymin": "0.043551568", "ymax": "0.26484036", "xmax": "0.8737701"}, "score": "0.9803375", "class": "fronton"}, {"bndbox": {"xmin": "0.14808102", "ymin": "0.03070629", "ymax": "0.26692158", "xmax": "0.8816227"}, "score": "0.30858895", "class": "fronton-partido"}], "true_label": 3}