{"num_predictions": [{"arco-herradura": 0}, {"dintel-adovelado": 0}, {"arco-lobulado": 0}, {"arco-medio-punto": 0}, {"arco-apuntado": 0}, {"vano-adintelado": 1}, {"fronton": 1}, {"arco-conopial": 0}, {"arco-trilobulado": 0}, {"serliana": 0}, {"ojo-de-buey": 0}, {"fronton-curvo": 0}, {"fronton-partido": 4}, {"columna-salomonica": 0}], "image": "../Data/Dataset-IGRB1092_14cls/04.barroco/casa_marqueses_de_cartagena_granada5.jpg", "object": [{"bndbox": {"xmin": "0.28103098", "ymin": "0.2019888", "ymax": "0.3980754", "xmax": "0.8181024"}, "score": "0.9991623", "class": "fronton-partido"}, {"bndbox": {"xmin": "0.39379844", "ymin": "0.50492793", "ymax": "1.0", "xmax": "0.6913986"}, "score": "0.99563295", "class": "vano-adintelado"}, {"bndbox": {"xmin": "0.26125976", "ymin": "0.0", "ymax": "0.08920765", "xmax": "0.8492557"}, "score": "0.9691572", "class": "fronton-partido"}, {"bndbox": {"xmin": "0.35186702", "ymin": "0.00041657448", "ymax": "0.08254697", "xmax": "0.85412425"}, "score": "0.27390218", "class": "fronton"}, {"bndbox": {"xmin": "0.4461196", "ymin": "0.0014358807", "ymax": "0.09410889", "xmax": "0.69421166"}, "score": "0.17125584", "class": "fronton-partido"}, {"bndbox": {"xmin": "0.38385054", "ymin": "0.20560071", "ymax": "0.37757292", "xmax": "0.6350728"}, "score": "0.05147317", "class": "fronton-partido"}], "true_label": 3}