{"num_predictions": [{"arco-herradura": 0}, {"dintel-adovelado": 0}, {"arco-lobulado": 0}, {"arco-medio-punto": 1}, {"arco-apuntado": 0}, {"vano-adintelado": 0}, {"fronton": 0}, {"arco-conopial": 0}, {"arco-trilobulado": 0}, {"serliana": 1}, {"ojo-de-buey": 0}, {"fronton-curvo": 0}, {"fronton-partido": 3}, {"columna-salomonica": 7}], "image": "../Data/Dataset-IGRB1092_14cls/04.barroco/facultad_derecho_granada5.jpg", "object": [{"bndbox": {"xmin": "0.46634513", "ymin": "0.6620874", "ymax": "0.8565193", "xmax": "0.77165276"}, "score": "0.99572754", "class": "arco-medio-punto"}, {"bndbox": {"xmin": "0.38796988", "ymin": "0.65746504", "ymax": "0.9961975", "xmax": "0.51101285"}, "score": "0.99482274", "class": "columna-salomonica"}, {"bndbox": {"xmin": "0.42669934", "ymin": "0.117753856", "ymax": "0.38413563", "xmax": "0.5062676"}, "score": "0.99482214", "class": "columna-salomonica"}, {"bndbox": {"xmin": "0.3364118", "ymin": "0.12813036", "ymax": "0.38538244", "xmax": "0.41276106"}, "score": "0.9944154", "class": "columna-salomonica"}, {"bndbox": {"xmin": "0.6851223", "ymin": "0.18263884", "ymax": "0.42401388", "xmax": "0.7624666"}, "score": "0.9912732", "class": "columna-salomonica"}, {"bndbox": {"xmin": "0.23167685", "ymin": "0.6304998", "ymax": "1.0", "xmax": "0.3483305"}, "score": "0.99069864", "class": "columna-salomonica"}, {"bndbox": {"xmin": "0.79813653", "ymin": "0.66494447", "ymax": "0.99292266", "xmax": "0.91757315"}, "score": "0.98740864", "class": "columna-salomonica"}, {"bndbox": {"xmin": "0.15837134", "ymin": "0.39031285", "ymax": "0.5530407", "xmax": "1.0"}, "score": "0.5133856", "class": "fronton-partido"}, {"bndbox": {"xmin": "0.27644318", "ymin": "0.0025183964", "ymax": "0.098326996", "xmax": "0.80756193"}, "score": "0.5009805", "class": "fronton-partido"}, {"bndbox": {"xmin": "0.18988788", "ymin": "0.3493604", "ymax": "0.56537724", "xmax": "0.6406047"}, "score": "0.09246052", "class": "fronton-partido"}, {"bndbox": {"xmin": "0.42880473", "ymin": "0.11684896", "ymax": "0.3657612", "xmax": "0.4570563"}, "score": "0.06822001", "class": "columna-salomonica"}, {"bndbox": {"xmin": "0.22080195", "ymin": "0.6610001", "ymax": "1.0", "xmax": "0.8560105"}, "score": "0.062092993", "class": "serliana"}], "true_label": 3}