{"num_predictions": [{"arco-herradura": 0}, {"dintel-adovelado": 0}, {"arco-lobulado": 0}, {"arco-medio-punto": 1}, {"arco-apuntado": 0}, {"vano-adintelado": 1}, {"fronton": 2}, {"arco-conopial": 0}, {"arco-trilobulado": 0}, {"serliana": 1}, {"ojo-de-buey": 0}, {"fronton-curvo": 1}, {"fronton-partido": 5}, {"columna-salomonica": 0}], "image": "../Data/Dataset-IGRB1092_14cls/04.barroco/iglesia_caridad_sevilla6.jpg", "object": [{"bndbox": {"xmin": "0.03883108", "ymin": "0.43872216", "ymax": "0.5555652", "xmax": "0.31430525"}, "score": "0.9972536", "class": "fronton"}, {"bndbox": {"xmin": "0.6965769", "ymin": "0.3506674", "ymax": "0.48483118", "xmax": "1.0"}, "score": "0.99571335", "class": "fronton"}, {"bndbox": {"xmin": "0.6926392", "ymin": "0.73071164", "ymax": "0.8461973", "xmax": "1.0"}, "score": "0.9934915", "class": "fronton-partido"}, {"bndbox": {"xmin": "0.014687186", "ymin": "0.78521115", "ymax": "0.8962166", "xmax": "0.2914915"}, "score": "0.99230766", "class": "fronton-partido"}, {"bndbox": {"xmin": "0.34558156", "ymin": "0.7617084", "ymax": "0.87103665", "xmax": "0.6702784"}, "score": "0.98295814", "class": "fronton-partido"}, {"bndbox": {"xmin": "0.29355374", "ymin": "0.7189495", "ymax": "0.87689954", "xmax": "0.93061876"}, "score": "0.6712652", "class": "fronton-partido"}, {"bndbox": {"xmin": "0.29565218", "ymin": "0.44490007", "ymax": "0.8122197", "xmax": "0.69045454"}, "score": "0.129615", "class": "arco-medio-punto"}, {"bndbox": {"xmin": "0.4840533", "ymin": "0.0070950505", "ymax": "0.21964896", "xmax": "0.5968012"}, "score": "0.10240987", "class": "vano-adintelado"}, {"bndbox": {"xmin": "0.0", "ymin": "0.7405985", "ymax": "0.9040222", "xmax": "0.646705"}, "score": "0.085658915", "class": "fronton-partido"}, {"bndbox": {"xmin": "0.66497666", "ymin": "0.73908323", "ymax": "0.85358995", "xmax": "1.0"}, "score": "0.08104512", "class": "fronton-curvo"}, {"bndbox": {"xmin": "0.2739115", "ymin": "0.48578557", "ymax": "0.8741309", "xmax": "0.70278865"}, "score": "0.06862583", "class": "serliana"}], "true_label": 3}