{"num_predictions": [{"arco-herradura": 0}, {"dintel-adovelado": 0}, {"arco-lobulado": 0}, {"arco-medio-punto": 0}, {"arco-apuntado": 1}, {"vano-adintelado": 2}, {"fronton": 0}, {"arco-conopial": 0}, {"arco-trilobulado": 0}, {"serliana": 1}, {"ojo-de-buey": 0}, {"fronton-curvo": 0}, {"fronton-partido": 0}, {"columna-salomonica": 0}], "image": "../Data/Dataset-IGRB1092_14cls/02.gotico/5bc9a11663f9b.jpg", "object": [{"bndbox": {"xmin": "0.10094727", "ymin": "0.18350509", "ymax": "0.66881174", "xmax": "0.88814276"}, "score": "0.9969416", "class": "arco-apuntado"}, {"bndbox": {"xmin": "0.33440992", "ymin": "0.61619234", "ymax": "0.9936655", "xmax": "0.6480208"}, "score": "0.61978", "class": "vano-adintelado"}, {"bndbox": {"xmin": "0.33168468", "ymin": "0.69800866", "ymax": "0.9733967", "xmax": "0.5011578"}, "score": "0.32766634", "class": "vano-adintelado"}, {"bndbox": {"xmin": "0.30634817", "ymin": "0.6012272", "ymax": "0.982584", "xmax": "0.7044442"}, "score": "0.07923811", "class": "serliana"}], "true_label": 1}