{"num_predictions": [{"arco-herradura": 0}, {"dintel-adovelado": 0}, {"arco-lobulado": 0}, {"arco-medio-punto": 0}, {"arco-apuntado": 1}, {"vano-adintelado": 0}, {"fronton": 0}, {"arco-conopial": 3}, {"arco-trilobulado": 2}, {"serliana": 0}, {"ojo-de-buey": 0}, {"fronton-curvo": 0}, {"fronton-partido": 0}, {"columna-salomonica": 0}], "image": "../Data/Dataset-IGRB1092_14cls/02.gotico/hospital_san_sebastian_cordoba.jpg", "object": [{"bndbox": {"xmin": "0.11659233", "ymin": "0.021952879", "ymax": "0.22501425", "xmax": "0.8183413"}, "score": "0.95475996", "class": "arco-conopial"}, {"bndbox": {"xmin": "0.33774713", "ymin": "0.556922", "ymax": "0.67939514", "xmax": "0.66585296"}, "score": "0.9244136", "class": "arco-trilobulado"}, {"bndbox": {"xmin": "0.29415303", "ymin": "0.23318243", "ymax": "0.41098982", "xmax": "0.7430185"}, "score": "0.89792764", "class": "arco-conopial"}, {"bndbox": {"xmin": "0.3292694", "ymin": "0.56752527", "ymax": "0.62332964", "xmax": "0.67498636"}, "score": "0.21326874", "class": "arco-conopial"}, {"bndbox": {"xmin": "0.3404197", "ymin": "0.54909146", "ymax": "0.6380578", "xmax": "0.59894353"}, "score": "0.15194798", "class": "arco-trilobulado"}, {"bndbox": {"xmin": "0.29664025", "ymin": "0.23442854", "ymax": "0.43574554", "xmax": "0.7415508"}, "score": "0.0555463", "class": "arco-apuntado"}], "true_label": 1}