{"num_predictions": [{"arco-herradura": 0}, {"dintel-adovelado": 0}, {"arco-lobulado": 0}, {"arco-medio-punto": 3}, {"arco-apuntado": 7}, {"vano-adintelado": 1}, {"fronton": 0}, {"arco-conopial": 1}, {"arco-trilobulado": 0}, {"serliana": 0}, {"ojo-de-buey": 0}, {"fronton-curvo": 0}, {"fronton-partido": 0}, {"columna-salomonica": 0}], "image": "../Data/Dataset-IGRB1092_14cls/02.gotico/santa_maria_del_mar_barcelona.jpg", "object": [{"bndbox": {"xmin": "0.31887937", "ymin": "0.44960847", "ymax": "0.75209886", "xmax": "0.69135803"}, "score": "0.9973151", "class": "arco-apuntado"}, {"bndbox": {"xmin": "0.8701721", "ymin": "0.3998378", "ymax": "0.48005745", "xmax": "0.97957623"}, "score": "0.9962657", "class": "arco-apuntado"}, {"bndbox": {"xmin": "0.026281552", "ymin": "0.41001433", "ymax": "0.48208228", "xmax": "0.15482564"}, "score": "0.9898504", "class": "arco-apuntado"}, {"bndbox": {"xmin": "0.635078", "ymin": "0.41481522", "ymax": "0.48321742", "xmax": "0.73404837"}, "score": "0.97712326", "class": "arco-apuntado"}, {"bndbox": {"xmin": "0.76581746", "ymin": "0.15417752", "ymax": "0.2122987", "xmax": "0.8417519"}, "score": "0.97704595", "class": "arco-apuntado"}, {"bndbox": {"xmin": "0.28155696", "ymin": "0.41929775", "ymax": "0.48746914", "xmax": "0.37863377"}, "score": "0.9640506", "class": "arco-apuntado"}, {"bndbox": {"xmin": "0.18953285", "ymin": "0.15945597", "ymax": "0.21365353", "xmax": "0.26337332"}, "score": "0.93479455", "class": "arco-apuntado"}, {"bndbox": {"xmin": "0.4013907", "ymin": "0.7921834", "ymax": "0.99395", "xmax": "0.6038814"}, "score": "0.14207725", "class": "vano-adintelado"}, {"bndbox": {"xmin": "0.18883947", "ymin": "0.1578462", "ymax": "0.2168648", "xmax": "0.26061514"}, "score": "0.073143646", "class": "arco-medio-punto"}, {"bndbox": {"xmin": "0.63344127", "ymin": "0.40438458", "ymax": "0.48994154", "xmax": "0.7383433"}, "score": "0.06193599", "class": "arco-medio-punto"}, {"bndbox": {"xmin": "0.86127347", "ymin": "0.3889261", "ymax": "0.47703615", "xmax": "0.99425185"}, "score": "0.054196816", "class": "arco-medio-punto"}, {"bndbox": {"xmin": "0.63002074", "ymin": "0.40836334", "ymax": "0.46021232", "xmax": "0.74164027"}, "score": "0.050916873", "class": "arco-conopial"}], "true_label": 1}