{"num_predictions": [{"arco-herradura": 1}, {"dintel-adovelado": 2}, {"arco-lobulado": 0}, {"arco-medio-punto": 0}, {"arco-apuntado": 0}, {"vano-adintelado": 0}, {"fronton": 0}, {"arco-conopial": 0}, {"arco-trilobulado": 0}, {"serliana": 0}, {"ojo-de-buey": 0}, {"fronton-curvo": 0}, {"fronton-partido": 0}, {"columna-salomonica": 0}], "image": "../Data/Dataset-IGRB1092_14cls/01.musulman/5c1b60d5c92de.jpg", "object": [{"bndbox": {"xmin": "0.21960424", "ymin": "0.19175133", "ymax": "0.6841425", "xmax": "0.77233285"}, "score": "0.99931383", "class": "arco-herradura"}, {"bndbox": {"xmin": "0.14650287", "ymin": "0.0", "ymax": "0.09437288", "xmax": "0.84785205"}, "score": "0.9967043", "class": "dintel-adovelado"}, {"bndbox": {"xmin": "0.20714714", "ymin": "0.0", "ymax": "0.07649308", "xmax": "0.5291827"}, "score": "0.15850319", "class": "dintel-adovelado"}], "true_label": 0}