{"num_predictions": [{"arco-herradura": 5}, {"dintel-adovelado": 0}, {"arco-lobulado": 11}, {"arco-medio-punto": 0}, {"arco-apuntado": 0}, {"vano-adintelado": 0}, {"fronton": 0}, {"arco-conopial": 0}, {"arco-trilobulado": 0}, {"serliana": 0}, {"ojo-de-buey": 0}, {"fronton-curvo": 0}, {"fronton-partido": 0}, {"columna-salomonica": 1}], "image": "../Data/Dataset-IGRB1092_14cls/01.musulman/patio_yeso_reales_alcazares_sevilla2.jpg", "object": [{"bndbox": {"xmin": "0.37645158", "ymin": "0.44550797", "ymax": "0.60801107", "xmax": "0.5004221"}, "score": "0.9980788", "class": "arco-herradura"}, {"bndbox": {"xmin": "0.70374006", "ymin": "0.40552256", "ymax": "0.6007403", "xmax": "0.8169583"}, "score": "0.997364", "class": "arco-lobulado"}, {"bndbox": {"xmin": "0.8180529", "ymin": "0.42122644", "ymax": "0.609889", "xmax": "0.9402117"}, "score": "0.99723995", "class": "arco-lobulado"}, {"bndbox": {"xmin": "0.93647087", "ymin": "0.39985523", "ymax": "0.6048624", "xmax": "0.9999024"}, "score": "0.9971794", "class": "arco-lobulado"}, {"bndbox": {"xmin": "0.0026248314", "ymin": "0.4331331", "ymax": "0.62209547", "xmax": "0.05839258"}, "score": "0.9964001", "class": "arco-lobulado"}, {"bndbox": {"xmin": "0.056323536", "ymin": "0.43284288", "ymax": "0.61896706", "xmax": "0.1665044"}, "score": "0.99563473", "class": "arco-lobulado"}, {"bndbox": {"xmin": "0.4968874", "ymin": "0.4444179", "ymax": "0.61017644", "xmax": "0.6152523"}, "score": "0.9950654", "class": "arco-herradura"}, {"bndbox": {"xmin": "0.16525659", "ymin": "0.4290955", "ymax": "0.61208886", "xmax": "0.27645436"}, "score": "0.99372756", "class": "arco-lobulado"}, {"bndbox": {"xmin": "0.3879864", "ymin": "0.4135456", "ymax": "0.60180706", "xmax": "0.5678298"}, "score": "0.3681327", "class": "arco-herradura"}, {"bndbox": {"xmin": "0.6988501", "ymin": "0.41526946", "ymax": "0.60023123", "xmax": "0.9287791"}, "score": "0.17850181", "class": "arco-lobulado"}, {"bndbox": {"xmin": "0.3113856", "ymin": "0.24858634", "ymax": "0.5969133", "xmax": "0.6591864"}, "score": "0.10068447", "class": "arco-herradura"}, {"bndbox": {"xmin": "0.2211362", "ymin": "0.15941991", "ymax": "0.7402335", "xmax": "0.7051797"}, "score": "0.075144365", "class": "arco-herradura"}, {"bndbox": {"xmin": "0.97642297", "ymin": "0.3980774", "ymax": "0.59368503", "xmax": "1.0"}, "score": "0.060343668", "class": "arco-lobulado"}, {"bndbox": {"xmin": "0.042410564", "ymin": "0.43567452", "ymax": "0.60726756", "xmax": "0.27913436"}, "score": "0.05796531", "class": "arco-lobulado"}, {"bndbox": {"xmin": "0.70991224", "ymin": "0.22673848", "ymax": "0.57060736", "xmax": "0.96462667"}, "score": "0.056311626", "class": "arco-lobulado"}, {"bndbox": {"xmin": "0.8773912", "ymin": "0.4027737", "ymax": "0.59508103", "xmax": "0.980925"}, "score": "0.050323803", "class": "arco-lobulado"}, {"bndbox": {"xmin": "0.933776", "ymin": "0.3882367", "ymax": "0.5985242", "xmax": "0.99173546"}, "score": "0.05016829", "class": "columna-salomonica"}], "true_label": 0}