{"num_predictions": [{"arco-herradura": 0}, {"dintel-adovelado": 0}, {"arco-lobulado": 0}, {"arco-medio-punto": 6}, {"arco-apuntado": 0}, {"vano-adintelado": 1}, {"fronton": 0}, {"arco-conopial": 0}, {"arco-trilobulado": 0}, {"serliana": 1}, {"ojo-de-buey": 1}, {"fronton-curvo": 0}, {"fronton-partido": 0}, {"columna-salomonica": 0}], "image": "../Data/Dataset-IGRB1092_14cls/03.renacentista/5b8ed0cd00d7c.jpg", "object": [{"bndbox": {"xmin": "0.48407292", "ymin": "0.07334317", "ymax": "0.123557374", "xmax": "0.53639394"}, "score": "0.9960359", "class": "ojo-de-buey"}, {"bndbox": {"xmin": "0.41496283", "ymin": "0.56506985", "ymax": "0.6656183", "xmax": "0.5717191"}, "score": "0.9957973", "class": "arco-medio-punto"}, {"bndbox": {"xmin": "0.7365178", "ymin": "0.31708845", "ymax": "0.4244822", "xmax": "0.9467333"}, "score": "0.99086773", "class": "arco-medio-punto"}, {"bndbox": {"xmin": "0.07564385", "ymin": "0.3322647", "ymax": "0.42985153", "xmax": "0.22937648"}, "score": "0.98818713", "class": "arco-medio-punto"}, {"bndbox": {"xmin": "0.76896864", "ymin": "0.6964417", "ymax": "0.7646974", "xmax": "0.88523287"}, "score": "0.9868177", "class": "arco-medio-punto"}, {"bndbox": {"xmin": "0.1182435", "ymin": "0.68542993", "ymax": "0.7498328", "xmax": "0.21205182"}, "score": "0.98319054", "class": "arco-medio-punto"}, {"bndbox": {"xmin": "0.4287848", "ymin": "0.11654316", "ymax": "0.2254467", "xmax": "0.5769548"}, "score": "0.9812617", "class": "serliana"}, {"bndbox": {"xmin": "0.35564432", "ymin": "0.35010794", "ymax": "0.4868145", "xmax": "0.6208095"}, "score": "0.9312468", "class": "arco-medio-punto"}, {"bndbox": {"xmin": "0.44205123", "ymin": "0.11972278", "ymax": "0.2357335", "xmax": "0.57640254"}, "score": "0.102687135", "class": "vano-adintelado"}], "true_label": 2}