{"num_predictions": [{"arco-herradura": 0}, {"dintel-adovelado": 0}, {"arco-lobulado": 0}, {"arco-medio-punto": 1}, {"arco-apuntado": 0}, {"vano-adintelado": 2}, {"fronton": 1}, {"arco-conopial": 0}, {"arco-trilobulado": 0}, {"serliana": 3}, {"ojo-de-buey": 0}, {"fronton-curvo": 0}, {"fronton-partido": 1}, {"columna-salomonica": 0}], "image": "../Data/Dataset-IGRB1092_14cls/03.renacentista/palacio_carlos_v_granada10.jpg", "object": [{"bndbox": {"xmin": "0.29049084", "ymin": "0.57681555", "ymax": "0.99695385", "xmax": "0.75057536"}, "score": "0.9983504", "class": "vano-adintelado"}, {"bndbox": {"xmin": "0.1542389", "ymin": "0.42011195", "ymax": "0.56366855", "xmax": "0.8426091"}, "score": "0.9857885", "class": "fronton"}, {"bndbox": {"xmin": "0.256358", "ymin": "0.00761816", "ymax": "0.24501978", "xmax": "0.7793509"}, "score": "0.98215216", "class": "serliana"}, {"bndbox": {"xmin": "0.110965386", "ymin": "0.010027618", "ymax": "0.32473543", "xmax": "0.8898379"}, "score": "0.2061166", "class": "serliana"}, {"bndbox": {"xmin": "0.34134987", "ymin": "0.018479632", "ymax": "0.21832475", "xmax": "0.80203676"}, "score": "0.18735196", "class": "arco-medio-punto"}, {"bndbox": {"xmin": "0.38093784", "ymin": "0.006643", "ymax": "0.24751541", "xmax": "0.787693"}, "score": "0.15846896", "class": "vano-adintelado"}, {"bndbox": {"xmin": "0.06544419", "ymin": "0.045416117", "ymax": "0.30118534", "xmax": "0.931693"}, "score": "0.10024317", "class": "fronton-partido"}, {"bndbox": {"xmin": "0.21679221", "ymin": "0.60341424", "ymax": "0.990087", "xmax": "0.8260435"}, "score": "0.052349962", "class": "serliana"}], "true_label": 2}